setup.cfg
setup.py
JSONMapperHGMMPFork.egg-info/PKG-INFO
JSONMapperHGMMPFork.egg-info/SOURCES.txt
JSONMapperHGMMPFork.egg-info/dependency_links.txt
JSONMapperHGMMPFork.egg-info/not-zip-safe
JSONMapperHGMMPFork.egg-info/requires.txt
JSONMapperHGMMPFork.egg-info/top_level.txt
jsonmapper/__init__.py
jsonmapper/backend.py
jsonmapper/basehandlers.py
jsonmapper/mako_render_tools.py
jsonmapper/messages.py
jsonmapper/renderers.py
jsonmapper/routing.py
jsonmapper/test.py
jsonmapper/templates/forms.html