Metadata-Version: 1.0
Name: JSONMapperHGMMPFork
Version: 0.62.023
Summary: Mapping JSON to objects and vice versa, this is a product of Christopher Lenz and Matthew Good with slight modifications
Home-page: https://github.com/MartinPeschke/jsonmapper
Author: Martin Peschke
Author-email: martin@per-4.com
License: BSD
Platform: UNKNOWN
